Metadata-Version: 2.1
Name: stern
Version: 2.0
Summary: The stern module wants to show how easy and understandable Python syntax is
Home-page: https://github.com/VasilSalkov/stern
Author: saivan
Author-email: vasilsalkou@gmail.com
Classifier: Programming Language :: Python :: 3
Classifier: License :: OSI Approved :: GNU General Public License v3 (GPLv3)
Classifier: Operating System :: OS Independent
Requires-Python: >=3.5
